vkgdr-0.1.dist-info/top_level.txt
vkgdr-0.1.dist-info/LICENSE
vkgdr-0.1.dist-info/METADATA
vkgdr-0.1.dist-info/RECORD
vkgdr-0.1.dist-info/WHEEL
vkgdr/pycuda.py
vkgdr/py.typed
vkgdr/build.py
vkgdr/__init__.py
vkgdr/_vkgdr.abi3.so
